pplogger/__init__.py
pplogger/__version__.py
pplogger/pplogger.py
pplogger-4.2.0.dist-info/LICENSE.txt
pplogger-4.2.0.dist-info/METADATA
pplogger-4.2.0.dist-info/WHEEL
pplogger-4.2.0.dist-info/top_level.txt
pplogger-4.2.0.dist-info/RECORD
