Metadata-Version: 2.1
Name: pplogger
Version: 4.2.0
Summary: Logging helper
Home-page: https://github.com/peterpakos/pplogger
Author: Peter Pakos
Author-email: peter.pakos@wandisco.com
License: GPLv3
Keywords: log logger logging helper
Platform: UNKNOWN
Classifier: Programming Language :: Python :: 2
Classifier: Programming Language :: Python :: 2.7
Classifier: Programming Language :: Python :: 3
Classifier: Programming Language :: Python :: 3.4
Classifier: Programming Language :: Python :: 3.5
Classifier: Programming Language :: Python :: 3.6
Classifier: Programming Language :: Python :: 3.7
Classifier: License :: OSI Approved :: GNU General Public License v3 (GPLv3)
Classifier: Topic :: Software Development :: Libraries :: Python Modules
Classifier: Topic :: System :: Logging
